idcn.pth
idcn/__init__.py
idcn/releases/3.10/idlelib/CREDITS.txt
idcn/releases/3.10/idlelib/ChangeLog
idcn/releases/3.10/idlelib/HISTORY.txt
idcn/releases/3.10/idlelib/NEWS.txt
idcn/releases/3.10/idlelib/NEWS2x.txt
idcn/releases/3.10/idlelib/README.txt
idcn/releases/3.10/idlelib/TODO.txt
idcn/releases/3.10/idlelib/__init__.py
idcn/releases/3.10/idlelib/__main__.py
idcn/releases/3.10/idlelib/autocomplete.py
idcn/releases/3.10/idlelib/autocomplete_w.py
idcn/releases/3.10/idlelib/autoexpand.py
idcn/releases/3.10/idlelib/browser.py
idcn/releases/3.10/idlelib/calltip.py
idcn/releases/3.10/idlelib/calltip_w.py
idcn/releases/3.10/idlelib/codecontext.py
idcn/releases/3.10/idlelib/colorizer.py
idcn/releases/3.10/idlelib/config-extensions.def
idcn/releases/3.10/idlelib/config-highlight.def
idcn/releases/3.10/idlelib/config-keys.def
idcn/releases/3.10/idlelib/config-main.def
idcn/releases/3.10/idlelib/config.py
idcn/releases/3.10/idlelib/config_key.py
idcn/releases/3.10/idlelib/configdialog.py
idcn/releases/3.10/idlelib/debugger.py
idcn/releases/3.10/idlelib/debugger_r.py
idcn/releases/3.10/idlelib/debugobj.py
idcn/releases/3.10/idlelib/debugobj_r.py
idcn/releases/3.10/idlelib/delegator.py
idcn/releases/3.10/idlelib/dynoption.py
idcn/releases/3.10/idlelib/editor.py
idcn/releases/3.10/idlelib/extend.txt
idcn/releases/3.10/idlelib/filelist.py
idcn/releases/3.10/idlelib/format.py
idcn/releases/3.10/idlelib/grep.py
idcn/releases/3.10/idlelib/help.html
idcn/releases/3.10/idlelib/help.py
idcn/releases/3.10/idlelib/help_about.py
idcn/releases/3.10/idlelib/history.py
idcn/releases/3.10/idlelib/hyperparser.py
idcn/releases/3.10/idlelib/idle.bat
idcn/releases/3.10/idlelib/idle.py
idcn/releases/3.10/idlelib/idle.pyw
idcn/releases/3.10/idlelib/iomenu.py
idcn/releases/3.10/idlelib/macosx.py
idcn/releases/3.10/idlelib/mainmenu.py
idcn/releases/3.10/idlelib/multicall.py
idcn/releases/3.10/idlelib/outwin.py
idcn/releases/3.10/idlelib/parenmatch.py
idcn/releases/3.10/idlelib/pathbrowser.py
idcn-1.5.1.dist-info/licenses/LICENSE
idcn-1.5.1.dist-info/METADATA
idcn-1.5.1.dist-info/WHEEL
idcn-1.5.1.dist-info/top_level.txt
idcn-1.5.1.dist-info/RECORD
