Metadata-Version: 2.4
Name: idcn
Version: 1.5.1
Summary: IDLE Chinese Translation | IDLE 汉化包
Author-email: zetaloop <zetaloop@outlook.com>
License-Expression: MIT
Project-URL: Homepage, https://github.com/zetaloop/IDLE-CN
Classifier: Development Status :: 5 - Production/Stable
Classifier: Intended Audience :: Developers
Classifier: Intended Audience :: Education
Classifier: Topic :: Software Development :: Internationalization
Classifier: Topic :: Software Development :: Localization
Classifier: Programming Language :: Python
Classifier: Programming Language :: Python :: 3
Classifier: Programming Language :: Python :: 3.9
Classifier: Programming Language :: Python :: 3.10
Classifier: Programming Language :: Python :: 3.11
Classifier: Programming Language :: Python :: 3.12
Classifier: Programming Language :: Python :: 3.13
Classifier: Programming Language :: Python :: 3.14
Classifier: Operating System :: OS Independent
Classifier: Natural Language :: Chinese (Simplified)
Requires-Python: >=3.9
License-File: LICENSE
Dynamic: license-file
